dev/fpga/verilog_spi/counter_16bit.v
module counter_16bit(
  input wire clk50Mhz,
  input wire rst,
  input wire sig,
  output reg [15:0] cnt=0
  );
   
always@(posedge clk50Mhz or posedge rst)
  
begin
  
  if(rst) cnt <= 1'b0; 

  else if(sig) cnt <= cnt + 1; 

  end

 endmodule

dev/fpga/verilog_spi/tb_counter_16bit.v
`timescale 1ns/1ps
module tb_counter_16bit;
    reg CLK;
    wire [15:0] cnt;
    reg start_clk = 0;
    reg rst = 0;
    wire sig;

    counter_16bit uut (
        .clk50Mhz(CLK), 
        .rst(rst), 
        .cnt(cnt),
        .sig(sig)
    );
    always begin
        #1;
        if (start_clk == 1) begin
            CLK <= ~CLK;
        end
    end
    initial begin
        $dumpfile("tb_counter_16bit.vcd");
        $dumpvars(0, tb_counter_16bit);
        $display("start");
        CLK = 0;
        start_clk = 0;
        $display("0tick");
        #1;
        $display("1tick");
        start_clk = 1;
        #10;
        $display("10tick");
        #100;
        rst = 1;
        #100;
        rst= 0;
        #100;
        start_clk = 0;
        #100;
        rst= 0;
        #100;

        rst= 1;
        start_clk = 1;
        #100;
        start_clk = 0;
        #100;

        $finish;
    end

endmodule

tb_counter_16bit.vcd
$date
	Sat Mar 16 13:39:52 2024
$end
$version
	Icarus Verilog
$end
$timescale
	1ps
$end
$scope module tb_counter_16bit $end
$var wire 16 ! cnt [15:0] $end
$var reg 1 " CLK $end
$var reg 1 # rst $end
$var reg 1 $ sig $end
$var reg 1 % start_clk $end
$scope module uut $end
$var wire 1 " clk50Mhz $end
$var wire 1 # rst $end
$var wire 1 $ sig $end
$var reg 16 & cnt [15:0] $end
$upscope $end
$upscope $end
$enddefinitions $end
$comment Show the parameter values. $end
$dumpall
$end
#0
$dumpvars
b0 &
0%
1$
0#
0"
b0 !
$end
#1000
1%
#2000
b1 !
b1 &
1"
#3000
0"
#4000
b10 !
b10 &
1"
#5000
0"
#6000
b11 !
b11 &
1"
#7000
0"
#8000
b100 !
b100 &
1"
#9000
0"
#10000
b101 !
b101 &
1"
#11000
0"
#12000
b110 !
b110 &
1"
#13000
0"
#14000
b111 !
b111 &
1"
#15000
0"
#16000
b1000 !
b1000 &
1"
#17000
0"
#18000
b1001 !
b1001 &
1"
#19000
0"
#20000
b1010 !
b1010 &
1"
#21000
0"
#22000
b1011 !
b1011 &
1"
#23000
0"
#24000
b1100 !
b1100 &
1"
#25000
0"
#26000
b1101 !
b1101 &
1"
#27000
0"
#28000
b1110 !
b1110 &
1"
#29000
0"
#30000
b1111 !
b1111 &
1"
#31000
0"
#32000
b10000 !
b10000 &
1"
#33000
0"
#34000
b10001 !
b10001 &
1"
#35000
0"
#36000
b10010 !
b10010 &
1"
#37000
0"
#38000
b10011 !
b10011 &
1"
#39000
0"
#40000
b10100 !
b10100 &
1"
#41000
0"
#42000
b10101 !
b10101 &
1"
#43000
0"
#44000
b10110 !
b10110 &
1"
#45000
0"
#46000
b10111 !
b10111 &
1"
#47000
0"
#48000
b11000 !
b11000 &
1"
#49000
0"
#50000
b11001 !
b11001 &
1"
#51000
0"
#52000
b11010 !
b11010 &
1"
#53000
0"
#54000
b11011 !
b11011 &
1"
#55000
0"
#56000
b11100 !
b11100 &
1"
#57000
0"
#58000
b11101 !
b11101 &
1"
#59000
0"
#60000
b11110 !
b11110 &
1"
#61000
0"
#62000
b11111 !
b11111 &
1"
#63000
0"
#64000
b100000 !
b100000 &
1"
#65000
0"
#66000
b100001 !
b100001 &
1"
#67000
0"
#68000
b100010 !
b100010 &
1"
#69000
0"
#70000
b100011 !
b100011 &
1"
#71000
0"
#72000
b100100 !
b100100 &
1"
#73000
0"
#74000
b100101 !
b100101 &
1"
#75000
0"
#76000
b100110 !
b100110 &
1"
#77000
0"
#78000
b100111 !
b100111 &
1"
#79000
0"
#80000
b101000 !
b101000 &
1"
#81000
0"
#82000
b101001 !
b101001 &
1"
#83000
0"
#84000
b101010 !
b101010 &
1"
#85000
0"
#86000
b101011 !
b101011 &
1"
#87000
0"
#88000
b101100 !
b101100 &
1"
#89000
0"
#90000
b101101 !
b101101 &
1"
#91000
0"
#92000
b101110 !
b101110 &
1"
#93000
0"
#94000
b101111 !
b101111 &
1"
#95000
0"
#96000
b110000 !
b110000 &
1"
#97000
0"
#98000
b110001 !
b110001 &
1"
#99000
0"
#100000
b110010 !
b110010 &
1"
#101000
0"
#102000
b110011 !
b110011 &
1"
#103000
0"
#104000
b110100 !
b110100 &
1"
#105000
0"
#106000
b110101 !
b110101 &
1"
#107000
0"
#108000
b110110 !
b110110 &
1"
#109000
0"
#110000
b110111 !
b110111 &
1"
#111000
b0 !
b0 &
0"
1#
