dev/fpga/rough_Time_Corelation_Analizer/plot_distributer.v

module plot_distributer(
	input wire clk,
	input wire [1:0] START,
	input wire [1:0] END,
	input wire [6:0] INTERVAL,
	input wire data_arrived,
	output reg [7:0] Addr,
	output reg Memory_add
);

parameter address_0 = 128;
reg [3:0] count = 0;

reg add_internal = 0;

always @(posedge clk) begin
	if (add_internal == 1'b1) begin
		if(count == 5) begin
			Memory_add <= 1'b0;
			count <= 0;
		end
		else begin
			count <= count + 1;
			Memory_add <= 1'b1;
		end
	end
	else count <= 0;
end


always @(posedge data_arrived) begin
	if (add_internal ==1'b1 && count == 5) begin
		add_internal = 0;
	end
	if(START == 2'b00 && END == 2'b11 && INTERVAL == 7'b0000000) begin
		Addr <= address_0;
		add_internal = 1;
	end
	else if(START == 2'b01 && END == 2'b10) begin
		Addr <= address_0 + INTERVAL;
		add_internal = 1;
	end
	else if(START == 2'b10 && END == 2'b01) begin
		Addr <= address_0 - INTERVAL;
		add_internal = 1;
	end
end
endmodule

dev/fpga/rough_Time_Corelation_Analizer/TDC.v
// Time to Digital Converter
// author: Gyeongjun Chae, San Kim
//
// clk : 500MHz
// Start[0]: pulse1 arrived at 0
// Start[1]: pulse2 arrived at 0
// End[0]: pulse1 arrived after INTERVAL
// End[1]: pulse2 arrived after INTERVAL
// data_arrived : 1 if data is arrived, it continues 2 clock cycles(4ns)
// INTERVAL : time between Start and End, 1 clock cycle is 2ns, at most 256ns(128 clock cycles)
//
// ex: pulse 1, 2 exactly arrived at 0ns, and after 10ns, pulse 1 arrived,
// at 0ns, data_arrived is 1, and 0 at 4ns
// at 0ns, INTERVAL is 0
// at 0ns, START_signal is 00, and END_signal is 11(if there was pulse short before, it will be neglected)
// then,
// at 14ns, data_arrived is 1 at 10ns, and 0,
// at 14ns, INTERVAL is 10 at 10ns
// at 14ns, START_signal is 11, and END_signal is 01, at 10ns
//
// after 128ns, counting will not be continued
module TDC(
	input wire clk,
	input wire pulse1,
	input wire pulse2,
	output reg [1:0] START_signal,
	output reg [1:0] END_signal,
	output reg [6:0] INTERVAL,
	output reg data_arrived
);


reg [6:0] count;
reg notedge_pulse;
wire pulse = pulse1 | pulse2;

initial
begin
	count = 0;
	START_signal <= 2'b00;
	END_signal <= 2'b00;
	notedge_pulse = 0;
	INTERVAL = 0;
	data_arrived = 0;
end


always @(posedge clk) begin
	if(pulse) begin
		if (~notedge_pulse) begin
			if (pulse1 && pulse2) begin
				INTERVAL <= 0;
				data_arrived <= 1;
				START_signal <= 2'b00;
				END_signal <= 2'b11;
				data_arrived <= 1;
			end
			else begin
				if(count == 7'd127) begin
					count <= 0;
					END_signal <= {pulse1, pulse2};
				end
				else begin
					INTERVAL<=count;
					count <= 0;
					START_signal<=END_signal;
					END_signal <= {pulse1, pulse2};
					data_arrived <= 1;
				end
			end
			notedge_pulse <= 1;
		end
		count <= 0;
	end
	else begin
		notedge_pulse <= 0;
		case(count)
			7'd2: begin
				data_arrived <= 0;
				count <= count + 1;
			end
			7'd127: begin
				count <= count;
			end
			default: begin
				count <= count + 1;
			end
		endcase
	end
end


endmodule

dev/fpga/rough_Time_Corelation_Analizer/tb_plot_distributer.v
`timescale 1ns / 1ps

module tb_plot_distributer;
    wire [6:0] INTERVAL;
    wire data_arrived;
    wire [7:0] Addr;
    wire Memory_add;
      // Parameters
    reg pulse1;
    reg pulse2;
    reg clk;
    wire [1:0] START_signal;
    wire [1:0] END_signal;

  // Instantiate the TDC module
  TDC u1 (
    .pulse1(pulse1),
    .pulse2(pulse2),
    .clk(clk),
    .START_signal(START_signal),
    .END_signal(END_signal),
    .INTERVAL(INTERVAL),
    .data_arrived(data_arrived)
  );
    // Instantiate the Unit Under Test (UUT)
plot_distributer u2 (
    .clk(clk),
    .START(START_signal),
    .END(END_signal),
    .INTERVAL(INTERVAL),
    .data_arrived(data_arrived),
    .Addr(Addr),
    .Memory_add(Memory_add)
);

  // Clock generator
  always begin
    #1 clk = ~clk;
  end

  // Test sequence
  initial begin
    $dumpfile("tb_plot_distributer.vcd");
    $dumpvars(0, tb_plot_distributer);
    $dumpvars(1, u2);

    // Initialize Inputs
    clk = 0;
    pulse1 = 0;
    pulse2 = 0;
    #10 pulse1 = 1;
    #2 pulse1 = 0;
    #10 pulse2 = 1;
    #2 pulse2 = 0;
    #100 pulse1 = 1;
    #2 pulse1 = 0;
    #10 pulse2 = 0;
    #2 pulse2 = 0;
    #100pulse2 = 1;
    #2 pulse2 = 0;
    #10 pulse1 = 1;
    #2 pulse1 = 0;
    #2 pulse2 = 0;
    #10 pulse1 = 1;
    #2 pulse1 = 0;
    #100 pulse2 = 1;
    #2 pulse2 = 0;
    #10 pulse1 = 1;
    pulse2 = 1;
    #2 pulse1 = 0;
    pulse2 = 0;
    #50 $finish;
  end

endmodule

tb_plot_distributer.vcd
$date
	Tue Apr 16 10:12:09 2024
$end
$version
	Icarus Verilog
$end
$timescale
	1ps
$end
$scope module tb_plot_distributer $end
$var wire 1 ! data_arrived $end
$var wire 2 " START_signal [1:0] $end
$var wire 1 # Memory_add $end
$var wire 7 $ INTERVAL [6:0] $end
$var wire 2 % END_signal [1:0] $end
$var wire 8 & Addr [7:0] $end
$var reg 1 ' clk $end
$var reg 1 ( pulse1 $end
$var reg 1 ) pulse2 $end
$scope module u1 $end
$var wire 1 ' clk $end
$var wire 1 * pulse $end
$var wire 1 ( pulse1 $end
$var wire 1 ) pulse2 $end
$var reg 2 + END_signal [1:0] $end
$var reg 7 , INTERVAL [6:0] $end
$var reg 2 - START_signal [1:0] $end
$var reg 7 . count [6:0] $end
$var reg 1 ! data_arrived $end
$var reg 1 / notedge_pulse $end
$upscope $end
$scope module u2 $end
$var wire 2 0 END [1:0] $end
$var wire 7 1 INTERVAL [6:0] $end
$var wire 2 2 START [1:0] $end
$var wire 1 ' clk $end
$var wire 1 ! data_arrived $end
$var parameter 32 3 address_0 $end
$var reg 8 4 Addr [7:0] $end
$var reg 1 # Memory_add $end
$var reg 1 5 add_internal $end
$var reg 4 6 count [3:0] $end
$upscope $end
$upscope $end
$scope module tb_plot_distributer $end
$scope module u2 $end
$upscope $end
$upscope $end
$enddefinitions $end
$comment Show the parameter values. $end
$dumpall
b10000000 3
$end
#0
$dumpvars
b0 6
05
bx 4
b0 2
b0 1
b0 0
0/
b0 .
b0 -
b0 ,
b0 +
0*
0)
0(
0'
bx &
b0 %
b0 $
x#
b0 "
0!
$end
#1000
b1 .
1'
#2000
0'
#3000
b10 .
1'
#4000
0'
#5000
b11 .
1'
#6000
0'
#7000
b100 .
1'
#8000
0'
#9000
b101 .
1'
#10000
1*
0'
1(
#11000
1/
1!
b10 %
b10 +
b10 0
b0 .
b101 $
b101 ,
b101 1
1'
#12000
0*
0'
0(
#13000
b1 .
0/
1'
#14000
0'
#15000
b10 .
1'
#16000
0'
#17000
b11 .
0!
1'
#18000
0'
#19000
b100 .
1'
#20000
0'
#21000
b101 .
1'
#22000
1*
0'
1)
#23000
b1111011 &
b1111011 4
15
1/
1!
b1 %
b1 +
b1 0
b10 "
b10 -
b10 2
b0 .
1'
#24000
0*
0'
0)
#25000
b1 .
0/
1#
b1 6
1'
#26000
0'
#27000
b10 6
b10 .
1'
#28000
0'
#29000
b11 .
0!
b11 6
1'
#30000
0'
#31000
b100 6
b100 .
1'
#32000
0'
#33000
b101 .
b101 6
1'
#34000
0'
#35000
b0 6
0#
b110 .
1'
#36000
0'
#37000
b111 .
1#
b1 6
1'
#38000
0'
#39000
b10 6
b1000 .
1'
#40000
0'
#41000
b1001 .
b11 6
1'
#42000
0'
#43000
b100 6
b1010 .
1'
#44000
0'
#45000
b1011 .
b101 6
1'
#46000
0'
#47000
b0 6
0#
b1100 .
1'
#48000
0'
#49000
b1101 .
1#
b1 6
1'
#50000
0'
#51000
b10 6
b1110 .
1'
#52000
0'
#53000
b1111 .
b11 6
1'
#54000
0'
#55000
b100 6
b10000 .
1'
#56000
0'
#57000
b10001 .
b101 6
1'
#58000
0'
#59000
b0 6
0#
b10010 .
1'
#60000
0'
#61000
b10011 .
1#
b1 6
1'
#62000
0'
#63000
b10 6
b10100 .
1'
#64000
0'
#65000
b10101 .
b11 6
1'
#66000
0'
#67000
b100 6
b10110 .
1'
#68000
0'
#69000
b10111 .
b101 6
1'
#70000
0'
#71000
b0 6
0#
b11000 .
1'
#72000
0'
#73000
b11001 .
1#
b1 6
1'
#74000
0'
#75000
b10 6
b11010 .
1'
#76000
0'
#77000
b11011 .
b11 6
1'
#78000
0'
#79000
b100 6
b11100 .
1'
#80000
0'
#81000
b11101 .
b101 6
1'
#82000
0'
#83000
b0 6
0#
b11110 .
1'
#84000
0'
#85000
b11111 .
1#
b1 6
1'
#86000
0'
#87000
b10 6
b100000 .
1'
#88000
0'
#89000
b100001 .
b11 6
1'
#90000
0'
#91000
b100 6
b100010 .
1'
#92000
0'
#93000
b100011 .
b101 6
1'
#94000
0'
#95000
b0 6
0#
b100100 .
1'
#96000
0'
#97000
b100101 .
1#
b1 6
1'
#98000
0'
#99000
b10 6
b100110 .
1'
#100000
0'
#101000
b100111 .
b11 6
1'
#102000
0'
#103000
b100 6
b101000 .
1'
#104000
0'
#105000
b101001 .
b101 6
1'
#106000
0'
#107000
b0 6
0#
b101010 .
1'
#108000
0'
#109000
b101011 .
1#
b1 6
1'
#110000
0'
#111000
b10 6
b101100 .
1'
#112000
0'
#113000
b101101 .
b11 6
1'
#114000
0'
#115000
b100 6
b101110 .
1'
#116000
0'
#117000
b101111 .
b101 6
1'
#118000
0'
#119000
b0 6
0#
b110000 .
1'
#120000
0'
#121000
b110001 .
1#
b1 6
1'
#122000
0'
#123000
b10 6
b110010 .
1'
#124000
1*
0'
1(
#125000
b10110010 &
b10110010 4
1/
1!
b10 %
b10 +
b10 0
b1 "
b1 -
b1 2
b0 .
b110010 $
b110010 ,
b110010 1
b11 6
1'
#126000
0*
0'
0(
#127000
b100 6
b1 .
0/
1'
#128000
0'
#129000
b10 .
b101 6
1'
#130000
0'
#131000
b0 6
0#
b11 .
0!
1'
#132000
0'
#133000
b100 .
1#
b1 6
1'
#134000
0'
#135000
b10 6
b101 .
1'
#136000
0'
#137000
b110 .
b11 6
1'
#138000
0'
#139000
b100 6
b111 .
1'
#140000
0'
#141000
b1000 .
b101 6
1'
#142000
0'
#143000
b0 6
0#
b1001 .
1'
#144000
0'
#145000
b1010 .
1#
b1 6
1'
#146000
0'
#147000
b10 6
b1011 .
1'
#148000
0'
#149000
b1100 .
b11 6
1'
#150000
0'
#151000
b100 6
b1101 .
1'
#152000
0'
#153000
b1110 .
b101 6
1'
#154000
0'
#155000
b0 6
0#
b1111 .
1'
#156000
0'
#157000
b10000 .
1#
b1 6
1'
#158000
0'
#159000
b10 6
b10001 .
1'
#160000
0'
#161000
b10010 .
b11 6
1'
#162000
0'
#163000
b100 6
b10011 .
1'
#164000
0'
#165000
b10100 .
b101 6
1'
#166000
0'
#167000
b0 6
0#
b10101 .
1'
#168000
0'
#169000
b10110 .
1#
b1 6
1'
#170000
0'
#171000
b10 6
b10111 .
1'
#172000
0'
#173000
b11000 .
b11 6
1'
#174000
0'
#175000
b100 6
b11001 .
1'
#176000
0'
#177000
b11010 .
b101 6
1'
#178000
0'
#179000
b0 6
0#
b11011 .
1'
#180000
0'
#181000
b11100 .
1#
b1 6
1'
#182000
0'
#183000
b10 6
b11101 .
1'
#184000
0'
#185000
b11110 .
b11 6
1'
#186000
0'
#187000
b100 6
b11111 .
1'
#188000
0'
#189000
b100000 .
b101 6
1'
#190000
0'
#191000
b0 6
0#
b100001 .
1'
#192000
0'
#193000
b100010 .
1#
b1 6
1'
#194000
0'
#195000
b10 6
b100011 .
1'
#196000
0'
#197000
b100100 .
b11 6
1'
#198000
0'
#199000
b100 6
b100101 .
1'
#200000
0'
#201000
b100110 .
b101 6
1'
#202000
0'
#203000
b0 6
0#
b100111 .
1'
#204000
0'
#205000
b101000 .
1#
b1 6
1'
#206000
0'
#207000
b10 6
b101001 .
1'
#208000
0'
#209000
b101010 .
b11 6
1'
#210000
0'
#211000
b100 6
b101011 .
1'
#212000
0'
#213000
b101100 .
b101 6
1'
#214000
0'
#215000
b0 6
0#
b101101 .
1'
#216000
0'
#217000
b101110 .
1#
b1 6
1'
#218000
0'
#219000
b10 6
b101111 .
1'
#220000
0'
#221000
b110000 .
b11 6
1'
#222000
0'
#223000
b100 6
b110001 .
1'
#224000
0'
#225000
b110010 .
b101 6
1'
#226000
0'
#227000
b0 6
0#
b110011 .
1'
#228000
0'
#229000
b110100 .
1#
b1 6
1'
#230000
0'
#231000
b10 6
b110101 .
1'
#232000
0'
#233000
b110110 .
b11 6
1'
#234000
0'
#235000
b100 6
b110111 .
1'
#236000
0'
#237000
b111000 .
b101 6
1'
#238000
1*
0'
1)
#239000
b1001000 &
b1001000 4
b0 6
0#
1/
1!
b1 %
b1 +
b1 0
b10 "
b10 -
b10 2
b0 .
b111000 $
b111000 ,
b111000 1
1'
#240000
0*
0'
0)
#241000
b1 .
0/
1#
b1 6
1'
#242000
0'
#243000
b10 6
b10 .
1'
#244000
0'
#245000
b11 .
0!
b11 6
1'
#246000
0'
#247000
b100 6
b100 .
1'
#248000
0'
#249000
b101 .
b101 6
1'
#250000
1*
0'
1(
#251000
b10000101 &
b10000101 4
b0 6
0#
1/
1!
b10 %
b10 +
b10 0
b1 "
b1 -
b1 2
b0 .
b101 $
b101 ,
b101 1
1'
#252000
0*
0'
0(
#253000
b1 .
0/
1#
b1 6
1'
#254000
0'
#255000
b10 6
b10 .
1'
#256000
0'
#257000
b11 .
0!
b11 6
1'
#258000
0'
#259000
b100 6
b100 .
1'
#260000
0'
#261000
b101 .
b101 6
1'
#262000
0'
#263000
b0 6
0#
b110 .
1'
#264000
1*
0'
1(
#265000
1/
1!
b10 "
b10 -
b10 2
b0 .
b110 $
b110 ,
b110 1
1#
b1 6
1'
#266000
0*
0'
0(
#267000
b10 6
b1 .
0/
1'
#268000
0'
#269000
b10 .
b11 6
1'
#270000
0'
#271000
b100 6
b11 .
0!
1'
#272000
0'
#273000
b100 .
b101 6
1'
#274000
0'
#275000
b0 6
0#
b101 .
1'
#276000
0'
#277000
b110 .
1#
b1 6
1'
#278000
0'
#279000
b10 6
b111 .
1'
#280000
0'
#281000
b1000 .
b11 6
1'
#282000
0'
#283000
b100 6
b1001 .
1'
#284000
0'
#285000
b1010 .
b101 6
1'
#286000
0'
#287000
b0 6
0#
b1011 .
1'
#288000
0'
#289000
b1100 .
1#
b1 6
1'
#290000
0'
#291000
b10 6
b1101 .
1'
#292000
0'
#293000
b1110 .
b11 6
1'
#294000
0'
#295000
b100 6
b1111 .
1'
#296000
0'
#297000
b10000 .
b101 6
1'
#298000
0'
#299000
b0 6
0#
b10001 .
1'
#300000
0'
#301000
b10010 .
1#
b1 6
1'
#302000
0'
#303000
b10 6
b10011 .
1'
#304000
0'
#305000
b10100 .
b11 6
1'
#306000
0'
#307000
b100 6
b10101 .
1'
#308000
0'
#309000
b10110 .
b101 6
1'
#310000
0'
#311000
b0 6
0#
b10111 .
1'
#312000
0'
#313000
b11000 .
1#
b1 6
1'
#314000
0'
#315000
b10 6
b11001 .
1'
#316000
0'
#317000
b11010 .
b11 6
1'
#318000
0'
#319000
b100 6
b11011 .
1'
#320000
0'
#321000
b11100 .
b101 6
1'
#322000
0'
#323000
b0 6
0#
b11101 .
1'
#324000
0'
#325000
b11110 .
1#
b1 6
1'
#326000
0'
#327000
b10 6
b11111 .
1'
#328000
0'
#329000
b100000 .
b11 6
1'
#330000
0'
#331000
b100 6
b100001 .
1'
#332000
0'
#333000
b100010 .
b101 6
1'
#334000
0'
#335000
b0 6
0#
b100011 .
1'
#336000
0'
#337000
b100100 .
1#
b1 6
1'
#338000
0'
#339000
b10 6
b100101 .
1'
#340000
0'
#341000
b100110 .
b11 6
1'
#342000
0'
#343000
b100 6
b100111 .
1'
#344000
0'
#345000
b101000 .
b101 6
1'
#346000
0'
#347000
b0 6
0#
b101001 .
1'
#348000
0'
#349000
b101010 .
1#
b1 6
1'
#350000
0'
#351000
b10 6
b101011 .
1'
#352000
0'
#353000
b101100 .
b11 6
1'
#354000
0'
#355000
b100 6
b101101 .
1'
#356000
0'
#357000
b101110 .
b101 6
1'
#358000
0'
#359000
b0 6
0#
b101111 .
1'
#360000
0'
#361000
b110000 .
1#
b1 6
1'
#362000
0'
#363000
b10 6
b110001 .
1'
#364000
0'
#365000
b110010 .
b11 6
1'
#366000
1*
0'
1)
#367000
b1001110 &
b1001110 4
b100 6
1/
1!
b1 %
b1 +
b1 0
b0 .
b110010 $
b110010 ,
b110010 1
1'
#368000
0*
0'
0)
#369000
b1 .
0/
b101 6
1'
#370000
0'
#371000
b0 6
0#
b10 .
1'
#372000
0'
#373000
b11 .
0!
1#
b1 6
1'
#374000
0'
#375000
b10 6
b100 .
1'
#376000
0'
#377000
b101 .
b11 6
1'
#378000
1*
0'
1)
1(
#379000
b10000000 &
b10000000 4
b100 6
b0 .
1/
b11 %
b11 +
b11 0
b0 "
b0 -
b0 2
1!
b0 $
b0 ,
b0 1
1'
#380000
0*
0'
0)
0(
#381000
b1 .
0/
b101 6
1'
#382000
0'
#383000
b0 6
0#
b10 .
1'
#384000
0'
#385000
b11 .
0!
1#
b1 6
1'
#386000
0'
#387000
b10 6
b100 .
1'
#388000
0'
#389000
b101 .
b11 6
1'
#390000
0'
#391000
b100 6
b110 .
1'
#392000
0'
#393000
b111 .
b101 6
1'
#394000
0'
#395000
b0 6
0#
b1000 .
1'
#396000
0'
#397000
b1001 .
1#
b1 6
1'
#398000
0'
#399000
b10 6
b1010 .
1'
#400000
0'
#401000
b1011 .
b11 6
1'
#402000
0'
#403000
b100 6
b1100 .
1'
#404000
0'
#405000
b1101 .
b101 6
1'
#406000
0'
#407000
b0 6
0#
b1110 .
1'
#408000
0'
#409000
b1111 .
1#
b1 6
1'
#410000
0'
#411000
b10 6
b10000 .
1'
#412000
0'
#413000
b10001 .
b11 6
1'
#414000
0'
#415000
b100 6
b10010 .
1'
#416000
0'
#417000
b10011 .
b101 6
1'
#418000
0'
#419000
b0 6
0#
b10100 .
1'
#420000
0'
#421000
b10101 .
1#
b1 6
1'
#422000
0'
#423000
b10 6
b10110 .
1'
#424000
0'
#425000
b10111 .
b11 6
1'
#426000
0'
#427000
b100 6
b11000 .
1'
#428000
0'
#429000
b11001 .
b101 6
1'
