dev/fpga/rough_Time_Corelation_Analizer/Pulse_Shaper.v
module Pulse_Shaper(
	input wire clk,// 500MHz
	input wire channel,
	output reg pulse
);

reg [7:0] count; // 8 bit counter for dead time:60ns, pulse width:2ns
reg activate;

initial begin
    activate = 0;
    count <= 8'h00;
	pulse <= 0;
end


always @(posedge channel) begin
    if(channel) begin
        activate = 1;
    end
end


always @(posedge clk) begin
	if(activate) begin
		count[7:0] <= count + 1;
		case(count)
			8'd0: pulse <= 1;
			8'd30: begin
				pulse <= 0;
				activate = 0;
				count <= 8'h00;
			end
			default: pulse <= 0;
		endcase
	end
end

endmodule

dev/fpga/rough_Time_Corelation_Analizer/tb_Pulse_Shaper.v
`timescale 1ns/1ps

module tb_Pulse_Shaper;

    reg clk;
    reg channel;
    wire pulse;

    // Instantiate the Pulse_Shaper
    Pulse_Shaper uut (
        .clk(clk),
        .channel(channel),
        .pulse(pulse)
    );

    // Clock generator
    always begin
        #1 clk = ~clk;
    end

    // Test sequence
    initial begin
        // Initialize signals
        $dumpfile("tb_Pulse_Shaper.vcd");
        $dumpvars(0, tb_Pulse_Shaper);
        clk = 0;
        channel = 0;

        // Apply test vectors
        #10 channel = 1; // Trigger pulse
        #20 channel = 0; // Stop pulse
        #500 channel = 1; // Trigger pulse again
        #1 channel = 0; // Stop pulse again
        #1 channel = 1; // Trigger pulse again
        #1 channel = 0; // Stop pulse again
        #1 channel = 1; // Trigger pulse again
        #1 channel = 0; // Stop pulse again
        #1 channel = 1; // Trigger pulse again
        #1 channel = 0; // Stop pulse again
        #1 channel = 1; // Trigger pulse again
        #1 channel = 0; // Stop pulse again
        #1 channel = 1; // Trigger pulse again
        #1 channel = 0; // Stop pulse again

        // End of test
        #40 $finish;
    end

    // Monitor
    initial begin
        $monitor("At time %d, channel = %b, pulse = %b", $time, channel, pulse);
    end

endmodule

tb_Pulse_Shaper.vcd
$date
	Tue Apr 16 07:41:02 2024
$end
$version
	Icarus Verilog
$end
$timescale
	1ps
$end
$scope module tb_Pulse_Shaper $end
$var wire 1 ! pulse $end
$var reg 1 " channel $end
$var reg 1 # clk $end
$scope module uut $end
$var wire 1 " channel $end
$var wire 1 # clk $end
$var reg 1 $ activate $end
$var reg 8 % count [7:0] $end
$var reg 1 ! pulse $end
$upscope $end
$upscope $end
$enddefinitions $end
$comment Show the parameter values. $end
$dumpall
$end
#0
$dumpvars
b0 %
0$
0#
0"
0!
$end
#1000
1#
#2000
0#
#3000
1#
#4000
0#
#5000
1#
#6000
0#
#7000
1#
#8000
0#
#9000
1#
#10000
1$
0#
1"
#11000
1!
b1 %
1#
#12000
0#
#13000
0!
b10 %
1#
#14000
0#
#15000
b11 %
1#
#16000
0#
#17000
b100 %
1#
#18000
0#
#19000
b101 %
1#
#20000
0#
#21000
b110 %
1#
#22000
0#
#23000
b111 %
1#
#24000
0#
#25000
b1000 %
1#
#26000
0#
#27000
b1001 %
1#
#28000
0#
#29000
b1010 %
1#
#30000
0#
0"
#31000
b1011 %
1#
#32000
0#
#33000
b1100 %
1#
#34000
0#
#35000
b1101 %
1#
#36000
0#
#37000
b1110 %
1#
#38000
0#
#39000
b1111 %
1#
#40000
0#
#41000
b10000 %
1#
#42000
0#
#43000
b10001 %
1#
#44000
0#
#45000
b10010 %
1#
#46000
0#
#47000
b10011 %
1#
#48000
0#
#49000
b10100 %
1#
#50000
0#
#51000
b10101 %
1#
#52000
0#
#53000
b10110 %
1#
#54000
0#
#55000
b10111 %
1#
#56000
0#
#57000
b11000 %
1#
#58000
0#
#59000
b11001 %
1#
#60000
0#
#61000
b11010 %
1#
#62000
0#
#63000
b11011 %
1#
#64000
0#
#65000
b11100 %
1#
#66000
0#
#67000
b11101 %
1#
#68000
0#
#69000
b11110 %
1#
#70000
0#
#71000
b0 %
0$
1#
